flake8_only_english/__init__.py
flake8_only_english/checker.py
flake8_only_english-0.3.3.dist-info/licenses/LICENSE
flake8_only_english-0.3.3.dist-info/METADATA
flake8_only_english-0.3.3.dist-info/WHEEL
flake8_only_english-0.3.3.dist-info/entry_points.txt
flake8_only_english-0.3.3.dist-info/top_level.txt
flake8_only_english-0.3.3.dist-info/RECORD
