Metadata-Version: 2.4
Name: flake8-only-english
Version: 0.3.3
Summary: Flake8 plugin to detect non-English comments and string literals
Author: AlgorithmAlchemy
License: MIT
Keywords: flake8,linter,comments,strings,non-english,ascii,code-quality,static-analysis,plugin,python,code style,quality assurance,code standards
Classifier: Development Status :: 5 - Production/Stable
Classifier: Intended Audience :: Developers
Classifier: Topic :: Software Development :: Quality Assurance
Classifier: Topic :: Software Development :: Libraries :: Python Modules
Classifier: Topic :: Text Processing :: Linguistic
Classifier: Framework :: Flake8
Classifier: Programming Language :: Python :: 3
Classifier: Programming Language :: Python :: 3.8
Classifier: Programming Language :: Python :: 3.9
Classifier: Programming Language :: Python :: 3.10
Classifier: Programming Language :: Python :: 3.11
Classifier: Programming Language :: Python :: 3.12
Classifier: Programming Language :: Python :: 3.13
Classifier: License :: OSI Approved :: MIT License
Classifier: Operating System :: OS Independent
Requires-Python: >=3.8
License-File: LICENSE
Requires-Dist: regex>=2021.4.4
Dynamic: license-file
